aiotsmart/__init__.py
aiotsmart/const.py
aiotsmart/discovery.py
aiotsmart/exceptions.py
aiotsmart/models.py
aiotsmart/py.typed
aiotsmart/tsmart.py
aiotsmart/util.py
aiotsmart-1.1.1.dist-info/METADATA
aiotsmart-1.1.1.dist-info/WHEEL
aiotsmart-1.1.1.dist-info/licenses/LICENSE.md
aiotsmart-1.1.1.dist-info/RECORD
