Metadata-Version: 2.4
Name: aiotsmart
Version: 1.1.1
Summary: Asynchronous Python client for TSmart.
Project-URL: Homepage, https://github.com/andrew-codechimp/python-tsmart
Project-URL: Repository, https://github.com/andrew-codechimp/python-tsmart
Project-URL: Documentation, https://github.com/andrew-codechimp/python-tsmart
Project-URL: Bug Tracker, https://github.com/andrew-codechimp/python-tsmart/issues
Project-URL: Changelog, https://github.com/andrew-codechimp/python-tsmart/releases
Author-email: Andrew Jackson <andrew@codechimp.org>
Maintainer-email: Andrew Jackson <andrew@codechimp.org>
License: MIT
License-File: LICENSE.md
Keywords: api,async,client
Classifier: Development Status :: 5 - Production/Stable
Classifier: Framework :: AsyncIO
Classifier: Intended Audience :: Developers
Classifier: Natural Language :: English
Classifier: Programming Language :: Python :: 3
Classifier: Programming Language :: Python :: 3.11
Classifier: Programming Language :: Python :: 3.12
Classifier: Programming Language :: Python :: 3.13
Classifier: Programming Language :: Python :: 3.14
Classifier: Topic :: Software Development :: Libraries :: Python Modules
Requires-Python: >=3.11
Requires-Dist: aiohttp>=3.0.0
Requires-Dist: asyncio-dgram>=2.2.0
Requires-Dist: yarl>=1.6.0
Provides-Extra: dev
Requires-Dist: aioresponses==0.7.8; extra == 'dev'
Requires-Dist: codespell==2.4.1; extra == 'dev'
Requires-Dist: covdefaults==2.3.0; extra == 'dev'
Requires-Dist: coverage[toml]==7.13.0; extra == 'dev'
Requires-Dist: mypy==1.19.0; extra == 'dev'
Requires-Dist: pre-commit-hooks==6.0.0; extra == 'dev'
Requires-Dist: pre-commit==4.5.0; extra == 'dev'
Requires-Dist: pylint==4.0.4; extra == 'dev'
Requires-Dist: pytest-asyncio==1.3.0; extra == 'dev'
Requires-Dist: pytest-cov==7.0.0; extra == 'dev'
Requires-Dist: pytest<9,>=8.3.4; extra == 'dev'
Requires-Dist: ruff==0.14.8; extra == 'dev'
Requires-Dist: safety==3.7.0; extra == 'dev'
Requires-Dist: syrupy==5.0.0; extra == 'dev'
Requires-Dist: tomli-w==1.1.0; extra == 'dev'
Requires-Dist: yamllint==1.37.1; extra == 'dev'
